<?xml version="1.0" encoding="utf-8" ?>
<dwsync>
<file name="redtry_logo2.png" server="produtos.redtry.com.br" local="132334305300000000" remote="132345522000000000" Dst="0" />
<file name="400X200.gif" server="produtos.redtry.com.br" local="132152775080000000" remote="132345522000000000" Dst="0" />
<file name="1920x500.gif" server="produtos.redtry.com.br" local="132152775060000000" remote="132345522000000000" Dst="0" />
<file name="40X40.gif" server="produtos.redtry.com.br" local="132152775080000000" remote="132345522000000000" Dst="0" />
<file name="100X125.gif" server="produtos.redtry.com.br" local="132152775060000000" remote="132345522000000000" Dst="0" />
<file name="icon_whats.PNG" server="produtos.redtry.com.br" local="132334457340000000" remote="132345522000000000" Dst="0" />
<file name="straps_colorido2.png" server="produtos.redtry.com.br" local="132344835360000000" remote="132345526200000000" Dst="0" />
<file name="straps_colorido4.png" server="produtos.redtry.com.br" local="132345539400000000" remote="132345549000000000" Dst="0" />
<file name="redtry_logo.PNG" server="produtos.redtry.com.br" local="132329381080000000" remote="132347355600000000" Dst="0" />
<file name="straps_R3D1.png" server="produtos.redtry.com.br" local="132344839520000000" remote="132347356800000000" Dst="0" />
<file name="straps_colorido1.png" server="produtos.redtry.com.br" local="132344834780000000" remote="132347356800000000" Dst="0" />
<file name="sup_cel.png" server="produtos.redtry.com.br" local="132346471940000000" remote="132347357400000000" Dst="0" />
<file name="straps_colorido3.png" server="produtos.redtry.com.br" local="132344837880000000" remote="132347358000000000" Dst="0" />
<file name="straps_marca1.png" server="produtos.redtry.com.br" local="132344838620000000" remote="132347358000000000" Dst="0" />
<file name="sup_note.png" server="produtos.redtry.com.br" local="132346473640000000" remote="132347358000000000" Dst="0" />
<file name="R_conj_brancos.png" server="produtos.redtry.com.br" local="132346467700000000" remote="132347358600000000" Dst="0" />
<file name="R_conj_rosa.png" server="produtos.redtry.com.br" local="132346468060000000" remote="132347358600000000" Dst="0" />
<file name="sup_computador3.png" server="produtos.redtry.com.br" local="132344807780000000" remote="132347358600000000" Dst="0" />
<file name="gato2_2.png" server="produtos.redtry.com.br" local="132344818800000000" remote="132347359200000000" Dst="0" />
<file name="sup_computador6.png" server="produtos.redtry.com.br" local="132344815880000000" remote="132347359200000000" Dst="0" />
<file name="gato2_1.png" server="produtos.redtry.com.br" local="132344817820000000" remote="132347359200000000" Dst="0" />
<file name="gato1_1.png" server="produtos.redtry.com.br" local="132344775160000000" remote="132347359800000000" Dst="0" />
<file name="gato1_2.png" server="produtos.redtry.com.br" local="132344776760000000" remote="132347359800000000" Dst="0" />
<file name="wall2_1.jpg" server="produtos.redtry.com.br" local="132344777660000000" remote="132347359800000000" Dst="0" />
<file name="wall2_2.jpg" server="produtos.redtry.com.br" local="132344778800000000" remote="132347359800000000" Dst="0" />
<file name="R_conj_vermelho.png" server="produtos.redtry.com.br" local="132346468560000000" remote="132347360400000000" Dst="0" />
<file name="sup_celular1.png" server="produtos.redtry.com.br" local="132344782620000000" remote="132347360400000000" Dst="0" />
<file name="sup_celular2.png" server="produtos.redtry.com.br" local="132344783520000000" remote="132347360400000000" Dst="0" />
<file name="100X125.gif" server="redtry.com.br" local="132152775060000000" remote="132347488800000000" Dst="0" />
<file name="1920x500.gif" server="redtry.com.br" local="132152775060000000" remote="132347488800000000" Dst="0" />
<file name="400X200.gif" server="redtry.com.br" local="132152775080000000" remote="132347488800000000" Dst="0" />
<file name="40X40.gif" server="redtry.com.br" local="132152775080000000" remote="132347488800000000" Dst="0" />
<file name="redtry_logo2.png" server="redtry.com.br" local="132334305300000000" remote="132347488800000000" Dst="0" />
<file name="redtry_logo.PNG" server="redtry.com.br" local="132329381080000000" remote="132347488800000000" Dst="0" />
<file name="icon_whats.PNG" server="redtry.com.br" local="132334457340000000" remote="132347488800000000" Dst="0" />
<file name="straps_R3D1.png" server="redtry.com.br" local="132344839520000000" remote="132347490000000000" Dst="0" />
<file name="straps_colorido1.png" server="redtry.com.br" local="132344834780000000" remote="132347490600000000" Dst="0" />
<file name="straps_colorido3.png" server="redtry.com.br" local="132344837880000000" remote="132347490000000000" Dst="0" />
<file name="straps_marca1.png" server="redtry.com.br" local="132344838620000000" remote="132347490600000000" Dst="0" />
<file name="sup_cel.png" server="redtry.com.br" local="132346471940000000" remote="132347490600000000" Dst="0" />
<file name="straps_colorido2.png" server="redtry.com.br" local="132344835360000000" remote="132347491200000000" Dst="0" />
<file name="sup_note.png" server="redtry.com.br" local="132346473640000000" remote="132347491200000000" Dst="0" />
<file name="straps_colorido4.png" server="redtry.com.br" local="132345539400000000" remote="132347492400000000" Dst="0" />
<file name="R_conj_brancos.png" server="redtry.com.br" local="132346467700000000" remote="132347491800000000" Dst="0" />
<file name="sup_computador3.png" server="redtry.com.br" local="132344807780000000" remote="132347493000000000" Dst="0" />
<file name="R_conj_rosa.png" server="redtry.com.br" local="132346468060000000" remote="132347493000000000" Dst="0" />
<file name="R_conj_vermelho.png" server="redtry.com.br" local="132346468560000000" remote="132347493000000000" Dst="0" />
<file name="sup_computador6.png" server="redtry.com.br" local="132344815880000000" remote="132347493000000000" Dst="0" />
<file name="gato1_1.png" server="redtry.com.br" local="132344775160000000" remote="132347493600000000" Dst="0" />
<file name="gato2_1.png" server="redtry.com.br" local="132344817820000000" remote="132347493600000000" Dst="0" />
<file name="wall2_1.jpg" server="redtry.com.br" local="132344777660000000" remote="132347493600000000" Dst="0" />
<file name="gato2_2.png" server="redtry.com.br" local="132344818800000000" remote="132347493000000000" Dst="0" />
<file name="wall2_2.jpg" server="redtry.com.br" local="132344778800000000" remote="132347493600000000" Dst="0" />
<file name="gato1_2.png" server="redtry.com.br" local="132344776760000000" remote="132347493600000000" Dst="0" />
<file name="sup_celular2.png" server="redtry.com.br" local="132344783520000000" remote="132347494200000000" Dst="0" />
<file name="sup_celular1.png" server="redtry.com.br" local="132344782620000000" remote="132347494200000000" Dst="0" />
<file name="youtube.png" server="redtry.com.br" local="129804876000000000" remote="129804876000000000" Dst="0" />
<file name="yahoo.png" server="redtry.com.br" local="129804876000000000" remote="129804876000000000" Dst="0" />
<file name="twitter.png" server="redtry.com.br" local="129804876000000000" remote="129804876000000000" Dst="0" />
<file name="robert_white_conj.png" server="redtry.com.br" local="132334404600000000" remote="132334404600000000" Dst="0" />
<file name="ripple_nordic.png" server="redtry.com.br" local="132334405800000000" remote="132334405800000000" Dst="0" />
<file name="project_watch_stand_baum.png" server="redtry.com.br" local="132334401600000000" remote="132334401600000000" Dst="0" />
<file name="prevlabel.gif" server="redtry.com.br" local="129804876000000000" remote="129804876000000000" Dst="0" />
<file name="previous.png" server="redtry.com.br" local="129804876000000000" remote="129804876000000000" Dst="0" />
<file name="page_nav_bg.png" server="redtry.com.br" local="129804876000000000" remote="129804876000000000" Dst="0" />
<file name="nordic_white_1920.png" server="redtry.com.br" local="132334394400000000" remote="132334394400000000" Dst="0" />
<file name="nextlabel.gif" server="redtry.com.br" local="129804876000000000" remote="129804876000000000" Dst="0" />
<file name="menu_box.png" server="redtry.com.br" local="129804876000000000" remote="129804876000000000" Dst="0" />
<file name="loading.gif" server="redtry.com.br" local="129804876000000000" remote="129804876000000000" Dst="0" />
<file name="linkedin.png" server="redtry.com.br" local="129804876000000000" remote="129804876000000000" Dst="0" />
<file name="icon_testimonial1.png" server="redtry.com.br" local="129804876000000000" remote="129804876000000000" Dst="0" />
<file name="icon_testimonial.png" server="redtry.com.br" local="129804876000000000" remote="129804876000000000" Dst="0" />
<file name="icon_services.png" server="redtry.com.br" local="129804876000000000" remote="129804876000000000" Dst="0" />
<file name="icon_portfolio.png" server="redtry.com.br" local="129804876000000000" remote="129804876000000000" Dst="0" />
<file name="icon_contact.png" server="redtry.com.br" local="129804876000000000" remote="129804876000000000" Dst="0" />
<file name="icon_about.png" server="redtry.com.br" local="129804876000000000" remote="129804876000000000" Dst="0" />
<file name="flickr.png" server="redtry.com.br" local="129804876000000000" remote="129804876000000000" Dst="0" />
<file name="facebook.png" server="redtry.com.br" local="129804876000000000" remote="129804876000000000" Dst="0" />
<file name="closelabel.gif" server="redtry.com.br" local="129804876000000000" remote="129804876000000000" Dst="0" />
<file name="140X140.gif" server="redtry.com.br" local="132152364000000000" remote="132152364000000000" Dst="0" />
<file name="location.png" server="redtry.com.br" local="132349763880000000" remote="132349773600000000" Dst="0" />
<file name="email.png" server="redtry.com.br" local="132349762180000000" remote="132349773600000000" Dst="0" />
<file name="whatsapp.png" server="redtry.com.br" local="132349763580000000" remote="132349773600000000" Dst="0" />
<file name="R_conj_diversos.webp" server="redtry.com.br" local="132349832040000000" remote="132349835400000000" Dst="0" />
<file name="gatos1.webp" server="redtry.com.br" local="132349834820000000" remote="132349835400000000" Dst="0" />
<file name="straps_R3D2.webp" server="redtry.com.br" local="132349833880000000" remote="132349836000000000" Dst="0" />
</dwsync>